babuin/__init__.py
babuin-0.0.6.dist-info/LICENSE.txt
babuin-0.0.6.dist-info/METADATA
babuin-0.0.6.dist-info/WHEEL
babuin-0.0.6.dist-info/top_level.txt
babuin-0.0.6.dist-info/RECORD
