Metadata-Version: 2.2
Name: babuin
Version: 0.0.6
Summary: Aboubakar
Home-page: 
Author: Boo4kin
Author-email: bkolyabu@gmail.com
License: MIT
Keywords: test
Classifier: Development Status :: 5 - Production/Stable
Classifier: Intended Audience :: Education
Classifier: Operating System :: Microsoft :: Windows :: Windows 10
Classifier: License :: OSI Approved :: MIT License
Classifier: Programming Language :: Python :: 3
License-File: LICENSE.txt
Dynamic: author
Dynamic: author-email
Dynamic: classifier
Dynamic: description
Dynamic: keywords
Dynamic: license
Dynamic: summary
